README.txt
setup.py
tcsv2png/__init__.py
tcsv2png/tcsv2png.py
tcsv2png.egg-info/PKG-INFO
tcsv2png.egg-info/SOURCES.txt
tcsv2png.egg-info/dependency_links.txt
tcsv2png.egg-info/entry_points.txt
tcsv2png.egg-info/top_level.txt
tcsv2png.egg-info/zip-safe