Metadata-Version: 1.0
Name: tcsv2png
Version: 1.0.0
Summary: Data visualization of csv data with a time column.
Home-page: https://github.com/bdelbosc/tcsv2png
Author: Benoit Delbosc
Author-email: bdelbosc@nuxeo.com
License: GPL
Download-URL: http://public.dev.nuxeo.com/~ben/tcsv2png/tcsv2png-1.0.0.tar.gz
Keywords: monitoring csv chart png gnuplot
Platform: UNKNOWN
Classifier: Development Status :: 4 - Beta
Classifier: Environment :: Console
Classifier: Intended Audience :: Developers
Classifier: Intended Audience :: Information Technology
Classifier: Intended Audience :: System Administrators
Classifier: Natural Language :: English
Classifier: License :: OSI Approved :: GNU General Public License (GPL)
Classifier: Operating System :: OS Independent
Classifier: Programming Language :: Python
Classifier: Topic :: Software Development :: Quality Assurance
Classifier: Topic :: System :: Monitoring
